{"options":{"validator":{"$jsonSchema":{"bsonType":"object","required":["username","email","passwordHash"],"properties":{"username":{"bsonType":"string"},"email":{"bsonType":"string","pattern":"^.+@.+\\..+$","description":"Musi być poprawnym adresem e-mail"},"passwordHash":{"bsonType":"string"},"measurements":{"bsonType":"array"},"workouts":{"bsonType":"array"},"registeredEvents":{"bsonType":"array"}}}}},"indexes":[{"v":{"$numberInt":"2"},"key":{"_id":{"$numberInt":"1"}},"name":"_id_"}],"uuid":"b69d593818aa4d82a1cc470f30b96926","collectionName":"users","type":"collection"}